forml/__init__.py
forml/_exception.py
forml/application/__init__.py
forml/application/_descriptor.py
forml/application/_strategy.py
forml/evaluation/__init__.py
forml/evaluation/_api.py
forml/evaluation/_method.py
forml/evaluation/_metric.py
forml/evaluation/_stage.py
forml/flow/__init__.py
forml/flow/_exception.py
forml/flow/_task.py
forml/flow/_code/__init__.py
forml/flow/_code/compiler.py
forml/flow/_code/target/__init__.py
forml/flow/_code/target/system.py
forml/flow/_code/target/user.py
forml/flow/_graph/__init__.py
forml/flow/_graph/atomic.py
forml/flow/_graph/port.py
forml/flow/_graph/span.py
forml/flow/_suite/__init__.py
forml/flow/_suite/assembly.py
forml/flow/_suite/clean.py
forml/flow/_suite/member.py
forml/io/__init__.py
forml/io/_input/__init__.py
forml/io/_input/_producer.py
forml/io/_input/extract.py
forml/io/_output/__init__.py
forml/io/_output/_consumer.py
forml/io/_output/commit.py
forml/io/asset/__init__.py
forml/io/asset/_access.py
forml/io/asset/_persistent.py
forml/io/asset/_directory/__init__.py
forml/io/asset/_directory/level/__init__.py
forml/io/asset/_directory/level/case.py
forml/io/asset/_directory/level/major.py
forml/io/asset/_directory/level/minor.py
forml/io/asset/_directory/level/root.py
forml/io/dsl/__init__.py
forml/io/dsl/_exception.py
forml/io/dsl/parser.py
forml/io/dsl/_struct/__init__.py
forml/io/dsl/_struct/frame.py
forml/io/dsl/_struct/kind.py
forml/io/dsl/_struct/series.py
forml/io/dsl/function/__init__.py
forml/io/dsl/function/_aggregate.py
forml/io/dsl/function/_comparison.py
forml/io/dsl/function/_conversion.py
forml/io/dsl/function/_datetime.py
forml/io/dsl/function/_logical.py
forml/io/dsl/function/_math.py
forml/io/dsl/function/_window.py
forml/io/layout/__init__.py
forml/io/layout/_codec.py
forml/io/layout/_external.py
forml/io/layout/_internal.py
forml/pipeline/__init__.py
forml/pipeline/ensemble/__init__.py
forml/pipeline/ensemble/_stacking.py
forml/pipeline/payload/__init__.py
forml/pipeline/payload/_convert.py
forml-0.93.dist-info/METADATA
forml-0.93.dist-info/WHEEL
forml-0.93.dist-info/entry_points.txt
forml-0.93.dist-info/licenses/LICENSE
forml-0.93.dist-info/licenses/NOTICE
forml-0.93.dist-info/RECORD
