Metadata-Version: 2.1
Name: forml
Version: 0.93
Summary: A development framework and MLOps platform for the lifecycle management of data science projects.
Project-URL: Homepage, http://forml.io/
Project-URL: Source, https://github.com/formlio/forml/
Project-URL: Documentation, https://docs.forml.io/
Project-URL: Issues, https://github.com/formlio/forml/issues/
Project-URL: Changelog, https://github.com/formlio/forml/blob/master/CHANGELOG.md
Author-email: ForML Development Team <info@forml.io>
License: Apache License 2.0
License-File: LICENSE
License-File: NOTICE
Classifier: Development Status :: 4 - Beta
Classifier: Environment :: Console
Classifier: Intended Audience :: Developers
Classifier: Intended Audience :: Science/Research
Classifier: License :: OSI Approved :: Apache Software License
Classifier: Programming Language :: Python :: 3.9
Classifier: Programming Language :: Python :: 3.10
Classifier: Topic :: Scientific/Engineering :: Artificial Intelligence
Classifier: Topic :: System :: Distributed Computing
Requires-Python: >=3.9
Requires-Dist: click
Requires-Dist: cloudpickle
Requires-Dist: jinja2
Requires-Dist: numpy
Requires-Dist: packaging>=20.0
Requires-Dist: pandas
Requires-Dist: pip
Requires-Dist: scikit-learn
Requires-Dist: setuptools
Requires-Dist: toml
Requires-Dist: tomli
Provides-Extra: all
Requires-Dist: forml[dask,graphviz,mlflow,rest,spark,sql]; extra == 'all'
Provides-Extra: dask
Requires-Dist: distributed; extra == 'dask'
Provides-Extra: dev
Requires-Dist: black[jupyter]; extra == 'dev'
Requires-Dist: flake8-bugbear; extra == 'dev'
Requires-Dist: flake8-colors; extra == 'dev'
Requires-Dist: flake8-typing-imports; extra == 'dev'
Requires-Dist: isort; extra == 'dev'
Requires-Dist: pip-tools; extra == 'dev'
Requires-Dist: pre-commit; extra == 'dev'
Requires-Dist: pycln; extra == 'dev'
Requires-Dist: pylint; extra == 'dev'
Requires-Dist: pytest-asyncio; extra == 'dev'
Requires-Dist: pytest-cov; extra == 'dev'
Requires-Dist: pytest-xdist; extra == 'dev'
Requires-Dist: starlette[full]; extra == 'dev'
Provides-Extra: docs
Requires-Dist: jupyter-client; extra == 'docs'
Requires-Dist: nbsphinx; extra == 'docs'
Requires-Dist: sphinx; extra == 'docs'
Requires-Dist: sphinx-copybutton; extra == 'docs'
Requires-Dist: sphinx-immaterial; extra == 'docs'
Requires-Dist: sphinxcontrib-details-directive; extra == 'docs'
Requires-Dist: sphinxcontrib-napoleon; extra == 'docs'
Requires-Dist: sphinxcontrib-spelling; extra == 'docs'
Provides-Extra: graphviz
Requires-Dist: graphviz; extra == 'graphviz'
Provides-Extra: mlflow
Requires-Dist: mlflow; extra == 'mlflow'
Provides-Extra: rest
Requires-Dist: starlette; extra == 'rest'
Requires-Dist: uvicorn; extra == 'rest'
Provides-Extra: spark
Requires-Dist: pyspark; extra == 'spark'
Provides-Extra: sql
Requires-Dist: duckdb-engine; extra == 'sql'
Requires-Dist: pandas[parquet]; extra == 'sql'
Requires-Dist: sqlalchemy>=2.0.0; extra == 'sql'
